adventlibs_SNOLDINATOR/__init__.py
adventlibs_SNOLDINATOR/advent_libs.py
adventlibs_SNOLDINATOR/advent_libs_astar.py
adventlibs_SNOLDINATOR/advent_libs_brute_path.py
adventlibs_SNOLDINATOR/advent_libs_heatmap.py
adventlibs_SNOLDINATOR/advent_libs_matrix.py
adventlibs_SNOLDINATOR/advent_libs_path.py
adventlibs_snoldinator-0.0.1.dist-info/METADATA
adventlibs_snoldinator-0.0.1.dist-info/WHEEL
adventlibs_snoldinator-0.0.1.dist-info/licenses/LICENSE
adventlibs_snoldinator-0.0.1.dist-info/RECORD
